brahmai/__init__.py
brahmai/_globals.py
brahmai/chat.py
brahmai/embeddings.py
brahmai/errors.py
brahmai/moderations.py
brahmai/skynet.py
brahmai/ZeroShot/__init__.py
brahmai/ZeroShot/image.py
brahmai/ZeroShot/text.py
brahmai/secnet_analyzer/__init__.py
brahmai/secnet_analyzer/analysis_explanation.py
brahmai/secnet_analyzer/analyzer_engine.py
brahmai/secnet_analyzer/analyzer_request.py
brahmai/secnet_analyzer/analyzer_utils.py
brahmai/secnet_analyzer/app_tracer.py
brahmai/secnet_analyzer/batch_analyzer_engine.py
brahmai/secnet_analyzer/dict_analyzer_result.py
brahmai/secnet_analyzer/entity_recognizer.py
brahmai/secnet_analyzer/local_recognizer.py
brahmai/secnet_analyzer/pattern.py
brahmai/secnet_analyzer/pattern_recognizer.py
brahmai/secnet_analyzer/recognizer_registry.py
brahmai/secnet_analyzer/recognizer_result.py
brahmai/secnet_analyzer/remote_recognizer.py
brahmai/secnet_analyzer/context_aware_enhancers/__init__.py
brahmai/secnet_analyzer/context_aware_enhancers/context_aware_enhancer.py
brahmai/secnet_analyzer/context_aware_enhancers/lemma_context_aware_enhancer.py
brahmai/secnet_analyzer/nlp_engine/__init__.py
brahmai/secnet_analyzer/nlp_engine/ner_model_configuration.py
brahmai/secnet_analyzer/nlp_engine/nlp_artifacts.py
brahmai/secnet_analyzer/nlp_engine/nlp_engine.py
brahmai/secnet_analyzer/nlp_engine/nlp_engine_provider.py
brahmai/secnet_analyzer/nlp_engine/spacy_nlp_engine.py
brahmai/secnet_analyzer/nlp_engine/stanza_nlp_engine.py
brahmai/secnet_analyzer/nlp_engine/transformers_nlp_engine.py
brahmai/secnet_analyzer/predefined_recognizers/__init__.py
brahmai/secnet_analyzer/predefined_recognizers/aba_routing_recognizer.py
brahmai/secnet_analyzer/predefined_recognizers/au_abn_recognizer.py
brahmai/secnet_analyzer/predefined_recognizers/au_acn_recognizer.py
brahmai/secnet_analyzer/predefined_recognizers/au_medicare_recognizer.py
brahmai/secnet_analyzer/predefined_recognizers/au_tfn_recognizer.py
brahmai-0.1.0a0.dist-info/METADATA
brahmai-0.1.0a0.dist-info/WHEEL
brahmai-0.1.0a0.dist-info/top_level.txt
brahmai-0.1.0a0.dist-info/RECORD
