Metadata-Version: 2.1
Name: brahmai
Version: 0.1.0a0
Summary: Python SDK to interact with BRAHMAI APIs.
Author: BRAHMAI
Author-email: hello@brahmai.in
Requires-Dist: spacy-loggers ==1.0.5
Requires-Dist: transformers ==4.39.2
Requires-Dist: tldextract ==5.1.2
Requires-Dist: phonenumbers ==8.13.33
Requires-Dist: cryptography ==42.0.5
Requires-Dist: pycryptodome ==3.20.0
Requires-Dist: spacy-huggingface-pipelines ==0.0.4
